{
  "1782": {"topics": {"Teaching Quality": "negative", "Workload": "negative"}},
  "1783": {"topics": {"Teaching Quality": "positive", "Accessibility": "positive"}},
  "1784": {"topics": {"Teaching Quality": "positive"}},
  "1785": {"topics": {"Teaching Quality": "positive", "Workload": "neutral"}},
  "1786": {"topics": {"Teaching Quality": "positive", "Workload": "neutral"}},
  "1787": {"topics": {"Teaching Quality": "negative", "Grading": "negative", "Accessibility": "negative", "Workload": "negative"}},
  "1788": {"topics": {"Teaching Quality": "negative", "Grading": "neutral"}},
  "1789": {"topics": {"Teaching Quality": "positive"}},
  "1790": {"topics": {"Teaching Quality": "positive", "Workload": "negative"}},
  "1791": {"topics": {"Teaching Quality": "negative"}},
  "1792": {"topics": {"Teaching Quality": "positive", "Grading": "positive"}},
  "1793": {"topics": {"Teaching Quality": "positive", "Grading": "negative", "Workload": "negative"}},
  "1794": {"topics": {"Teaching Quality": "negative"}},
  "1795": {"topics": {"Teaching Quality": "positive", "Accessibility": "positive"}},
  "1796": {"topics": {"Teaching Quality": "positive", "Exam Difficulty": "positive"}},
  "1797": {"topics": {"Teaching Quality": "positive", "Accessibility": "positive", "Workload": "positive", "Grading": "positive"}},
  "1798": {"topics": {"Teaching Quality": "positive"}},
  "1799": {"topics": {"Exam Difficulty": "positive", "Teaching Quality": "positive"}},
  "1800": {"topics": {"Teaching Quality": "neutral", "Accessibility": "positive"}},
  "1801": {"topics": {"Teaching Quality": "neutral", "Workload": "neutral", "Grading": "positive"}},
  "1802": {"topics": {"Teaching Quality": "negative", "Grading": "negative"}},
  "1803": {"topics": {"Teaching Quality": "positive", "Grading": "neutral"}},
  "1804": {"topics": {"Teaching Quality": "positive", "Workload": "negative"}},
  "1805": {"topics": {"Teaching Quality": "positive", "Grading": "neutral"}},
  "1806": {"topics": {"Teaching Quality": "negative", "Grading": "negative"}},
  "1807": {"topics": {"Teaching Quality": "positive"}},
  "1808": {"topics": {"Teaching Quality": "positive", "Exam Difficulty": "positive"}},
  "1809": {"topics": {"Teaching Quality": "negative", "Workload": "negative"}},
  "1810": {"topics": {"Teaching Quality": "positive", "Grading": "negative", "Exam Difficulty": "negative"}},
  "1811": {"topics": {"Teaching Quality": "positive", "Accessibility": "positive", "Grading": "positive"}},
  "1812": {"topics": {"Teaching Quality": "positive", "Accessibility": "positive"}},
  "1813": {"topics": {"Teaching Quality": "positive", "Workload": "negative", "Accessibility": "positive"}},
  "1814": {"topics": {"Teaching Quality": "positive"}},
  "1815": {"topics": {"Teaching Quality": "negative", "Workload": "negative", "Accessibility": "positive"}},
  "1816": {"topics": {"Teaching Quality": "positive"}},
  "1817": {"topics": {"Teaching Quality": "positive", "Exam Difficulty": "neutral"}},
  "1818": {"topics": {}},
  "1819": {"topics": {"Teaching Quality": "negative", "Accessibility": "positive", "Exam Difficulty": "negative"}},
  "1820": {"topics": {"Teaching Quality": "positive", "Exam Difficulty": "positive", "Workload": "negative"}},
  "1821": {"topics": {"Teaching Quality": "negative", "Workload": "negative"}},
  "1822": {"topics": {"Teaching Quality": "positive", "Grading": "negative"}},
  "1823": {"topics": {"Teaching Quality": "negative", "Grading": "negative"}},
  "1824": {"topics": {"Teaching Quality": "neutral", "Workload": "neutral"}},
  "1825": {"topics": {"Teaching Quality": "positive", "Grading": "negative", "Workload": "negative"}},
  "1826": {"topics": {"Teaching Quality": "positive"}},
  "1827": {"topics": {"Teaching Quality": "negative", "Workload": "negative"}},
  "1828": {"topics": {"Teaching Quality": "positive", "Exam Difficulty": "neutral"}},
  "1829": {"topics": {"Grading": "neutral", "Workload": "positive"}},
  "1830": {"topics": {"Teaching Quality": "positive", "Workload": "neutral", "Exam Difficulty": "positive"}},
  "1831": {"topics": {"Teaching Quality": "negative", "Grading": "positive", "Exam Difficulty": "positive"}},
  "1832": {"topics": {"Teaching Quality": "positive", "Grading": "negative", "Workload": "negative"}},
  "1833": {"topics": {"Teaching Quality": "positive"}},
  "1834": {"topics": {"Teaching Quality": "negative", "Grading": "neutral"}},
  "1835": {"topics": {"Teaching Quality": "positive", "Grading": "neutral"}},
  "1836": {"topics": {"Grading": "negative"}},
  "1837": {"topics": {"Teaching Quality": "positive", "Workload": "neutral"}},
  "1838": {"topics": {"Teaching Quality": "negative", "Exam Difficulty": "positive"}},
  "1839": {"topics": {"Teaching Quality": "positive", "Grading": "positive", "Workload": "positive"}},
  "1840": {"topics": {"Teaching Quality": "positive", "Grading": "positive"}},
  "1841": {"topics": {"Teaching Quality": "positive", "Accessibility": "positive"}},
  "1842": {"topics": {"Teaching Quality": "negative", "Grading": "positive"}},
  "1843": {"topics": {"Teaching Quality": "positive", "Grading": "negative"}},
  "1844": {"topics": {"Teaching Quality": "positive", "Workload": "neutral"}},
  "1845": {"topics": {"Teaching Quality": "positive", "Accessibility": "positive"}},
  "1846": {"topics": {"Teaching Quality": "negative", "Workload": "positive", "Grading": "neutral"}},
  "1847": {"topics": {"Teaching Quality": "positive", "Accessibility": "positive"}},
  "1848": {"topics": {"Workload": "negative", "Grading": "neutral"}},
  "1849": {"topics": {"Teaching Quality": "positive", "Workload": "negative"}},
  "1850": {"topics": {"Teaching Quality": "positive", "Accessibility": "positive"}},
  "1851": {"topics": {"Teaching Quality": "positive", "Grading": "neutral"}},
  "1852": {"topics": {}},
  "1853": {"topics": {"Teaching Quality": "negative"}},
  "1854": {"topics": {"Teaching Quality": "positive"}},
  "1855": {"topics": {"Teaching Quality": "positive"}},
  "1856": {"topics": {"Teaching Quality": "positive"}},
  "1857": {"topics": {"Grading": "positive", "Workload": "positive"}},
  "1858": {"topics": {"Teaching Quality": "positive", "Workload": "positive", "Exam Difficulty": "positive"}},
  "1859": {"topics": {"Teaching Quality": "positive", "Workload": "negative"}},
  "1860": {"topics": {"Teaching Quality": "positive", "Exam Difficulty": "negative"}},
  "1861": {"topics": {"Teaching Quality": "positive", "Grading": "negative", "Accessibility": "positive"}},
  "1862": {"topics": {"Teaching Quality": "positive", "Workload": "neutral"}},
  "1863": {"topics": {"Teaching Quality": "negative", "Accessibility": "negative"}},
  "1864": {"topics": {"Teaching Quality": "negative", "Workload": "negative"}},
  "1865": {"topics": {"Teaching Quality": "positive", "Accessibility": "positive"}},
  "1866": {"topics": {"Teaching Quality": "positive", "Grading": "positive"}},
  "1867": {"topics": {"Teaching Quality": "positive"}},
  "1868": {"topics": {"Teaching Quality": "positive", "Grading": "negative"}},
  "1869": {"topics": {"Teaching Quality": "positive"}},
  "1870": {"topics": {"Teaching Quality": "positive", "Accessibility": "positive"}},
  "1871": {"topics": {"Teaching Quality": "positive", "Grading": "negative", "Exam Difficulty": "positive"}},
  "1872": {"topics": {"Teaching Quality": "negative"}},
  "1873": {"topics": {"Teaching Quality": "positive", "Grading": "positive", "Exam Difficulty": "positive"}},
  "1874": {"topics": {"Teaching Quality": "negative"}},
  "1875": {"topics": {"Teaching Quality": "positive", "Grading": "positive"}},
  "1876": {"topics": {"Teaching Quality": "positive"}},
  "1877": {"topics": {"Grading": "negative", "Workload": "positive"}},
  "1878": {"topics": {"Teaching Quality": "positive", "Grading": "neutral"}},
  "1879": {"topics": {"Teaching Quality": "neutral", "Grading": "negative"}},
  "1880": {"topics": {"Teaching Quality": "positive", "Exam Difficulty": "neutral", "Workload": "positive"}},
  "1881": {"topics": {"Teaching Quality": "negative", "Workload": "negative", "Exam Difficulty": "negative"}},
  "1882": {"topics": {"Teaching Quality": "neutral", "Workload": "negative"}},
  "1883": {"topics": {"Grading": "negative", "Exam Difficulty": "negative"}},
  "1884": {"topics": {"Teaching Quality": "positive", "Grading": "positive", "Exam Difficulty": "positive"}},
  "1885": {"topics": {"Teaching Quality": "neutral", "Workload": "positive", "Exam Difficulty": "positive"}},
  "1886": {"topics": {"Teaching Quality": "positive", "Grading": "positive"}},
  "1887": {"topics": {"Teaching Quality": "positive", "Workload": "positive", "Exam Difficulty": "positive"}},
  "1888": {"topics": {"Teaching Quality": "positive"}},
  "1889": {"topics": {"Teaching Quality": "positive", "Accessibility": "positive", "Workload": "positive"}},
  "1890": {"topics": {"Teaching Quality": "positive", "Grading": "neutral"}},
  "1891": {"topics": {"Teaching Quality": "neutral", "Grading": "neutral"}},
  "1892": {"topics": {"Teaching Quality": "neutral", "Exam Difficulty": "negative", "Workload": "negative"}},
  "1893": {"topics": {"Teaching Quality": "positive", "Exam Difficulty": "positive"}},
  "1894": {"topics": {"Teaching Quality": "positive", "Workload": "negative", "Grading": "negative", "Accessibility": "positive"}},
  "1895": {"topics": {"Workload": "positive", "Exam Difficulty": "positive"}},
  "1896": {"topics": {"Teaching Quality": "negative", "Grading": "negative"}},
  "1897": {"topics": {"Teaching Quality": "positive"}},
  "1898": {"topics": {"Teaching Quality": "positive", "Accessibility": "positive", "Workload": "positive"}},
  "1899": {"topics": {"Teaching Quality": "negative", "Exam Difficulty": "negative"}},
  "1900": {"topics": {"Teaching Quality": "positive", "Grading": "neutral"}},
  "1901": {"topics": {"Teaching Quality": "negative", "Workload": "negative", "Grading": "negative", "Accessibility": "negative"}},
  "1902": {"topics": {"Teaching Quality": "positive", "Exam Difficulty": "positive"}},
  "1903": {"topics": {"Teaching Quality": "negative"}},
  "1904": {"topics": {"Teaching Quality": "positive", "Workload": "neutral"}},
  "1905": {"topics": {"Teaching Quality": "positive", "Workload": "negative", "Grading": "negative"}},
  "1906": {"topics": {"Teaching Quality": "positive"}},
  "1907": {"topics": {"Teaching Quality": "negative", "Exam Difficulty": "negative"}},
  "1908": {"topics": {"Teaching Quality": "negative", "Exam Difficulty": "negative"}},
  "1909": {"topics": {"Teaching Quality": "positive", "Accessibility": "positive", "Grading": "neutral"}},
  "1910": {"topics": {"Teaching Quality": "positive", "Workload": "positive"}},
  "1911": {"topics": {"Teaching Quality": "positive"}},
  "1912": {"topics": {"Teaching Quality": "positive", "Grading": "positive"}},
  "1913": {"topics": {"Teaching Quality": "negative", "Exam Difficulty": "negative"}},
  "1914": {"topics": {"Teaching Quality": "positive", "Workload": "positive"}},
  "1915": {"topics": {"Teaching Quality": "positive"}},
  "1916": {"topics": {"Teaching Quality": "positive", "Workload": "negative", "Grading": "negative"}},
  "1917": {"topics": {"Teaching Quality": "positive", "Grading": "positive"}},
  "1918": {"topics": {"Grading": "negative", "Accessibility": "positive"}},
  "1919": {"topics": {"Teaching Quality": "positive"}},
  "1920": {"topics": {"Teaching Quality": "negative", "Exam Difficulty": "negative", "Workload": "negative"}},
  "1921": {"topics": {"Teaching Quality": "positive"}},
  "1922": {"topics": {"Teaching Quality": "positive", "Workload": "neutral", "Accessibility": "positive"}},
  "1923": {"topics": {"Teaching Quality": "positive", "Accessibility": "positive"}},
  "1924": {"topics": {"Teaching Quality": "positive", "Grading": "negative"}},
  "1925": {"topics": {"Teaching Quality": "positive", "Workload": "neutral"}},
  "1926": {"topics": {"Teaching Quality": "positive", "Grading": "neutral"}},
  "1927": {"topics": {"Teaching Quality": "positive", "Grading": "neutral", "Exam Difficulty": "positive"}},
  "1928": {"topics": {"Teaching Quality": "positive", "Accessibility": "positive"}},
  "1929": {"topics": {"Teaching Quality": "positive", "Workload": "positive", "Grading": "neutral"}},
  "1930": {"topics": {"Teaching Quality": "neutral"}},
  "1931": {"topics": {"Teaching Quality": "positive", "Workload": "negative"}},
  "1932": {"topics": {"Teaching Quality": "negative", "Workload": "negative"}},
  "1933": {"topics": {"Teaching Quality": "positive"}},
  "1934": {"topics": {"Teaching Quality": "negative", "Grading": "negative"}},
  "1935": {"topics": {"Teaching Quality": "neutral", "Grading": "neutral"}},
  "1936": {"topics": {"Teaching Quality": "positive", "Grading": "positive"}},
  "1937": {"topics": {"Teaching Quality": "positive", "Grading": "positive"}},
  "1938": {"topics": {"Teaching Quality": "positive", "Workload": "positive"}},
  "1939": {"topics": {"Teaching Quality": "positive"}},
  "1940": {"topics": {"Teaching Quality": "positive", "Grading": "negative", "Workload": "negative"}},
  "1941": {"topics": {"Teaching Quality": "negative", "Workload": "negative", "Grading": "negative", "Exam Difficulty": "neutral"}},
  "1942": {"topics": {"Teaching Quality": "positive"}},
  "1943": {"topics": {"Teaching Quality": "negative", "Grading": "negative", "Workload": "positive"}},
  "1944": {"topics": {"Teaching Quality": "positive", "Grading": "negative"}},
  "1945": {"topics": {"Teaching Quality": "positive", "Grading": "positive"}},
  "1946": {"topics": {"Teaching Quality": "negative", "Grading": "negative"}},
  "1947": {"topics": {"Workload": "negative", "Grading": "negative"}},
  "1948": {"topics": {"Teaching Quality": "positive", "Grading": "negative"}},
  "1949": {"topics": {"Teaching Quality": "positive"}},
  "1950": {"topics": {"Teaching Quality": "positive", "Workload": "neutral"}},
  "1951": {"topics": {"Teaching Quality": "positive", "Grading": "neutral"}},
  "1952": {"topics": {"Teaching Quality": "negative"}},
  "1953": {"topics": {"Teaching Quality": "positive", "Workload": "negative"}},
  "1954": {"topics": {"Teaching Quality": "positive"}},
  "1955": {"topics": {"Teaching Quality": "positive", "Accessibility": "positive"}},
  "1956": {"topics": {"Teaching Quality": "positive", "Grading": "negative"}},
  "1957": {"topics": {"Teaching Quality": "negative", "Workload": "negative"}},
  "1958": {"topics": {"Teaching Quality": "negative"}},
  "1959": {"topics": {"Teaching Quality": "negative", "Grading": "negative"}},
  "1960": {"topics": {"Workload": "neutral", "Grading": "neutral", "Exam Difficulty": "positive"}},
  "1961": {"topics": {"Teaching Quality": "positive", "Grading": "negative", "Workload": "negative"}},
  "1962": {"topics": {"Teaching Quality": "negative"}},
  "1963": {"topics": {"Teaching Quality": "positive", "Exam Difficulty": "neutral"}},
  "1964": {"topics": {"Teaching Quality": "positive", "Grading": "positive"}},
  "1965": {"topics": {"Teaching Quality": "negative", "Grading": "negative", "Workload": "positive"}},
  "1966": {"topics": {"Teaching Quality": "positive"}},
  "1967": {"topics": {"Teaching Quality": "positive"}},
  "1968": {"topics": {"Teaching Quality": "negative", "Workload": "negative", "Grading": "negative"}},
  "1969": {"topics": {"Teaching Quality": "positive", "Grading": "neutral"}},
  "1970": {"topics": {"Teaching Quality": "positive"}},
  "1971": {"topics": {"Teaching Quality": "positive", "Grading": "negative", "Workload": "positive"}},
  "1972": {"topics": {}},
  "1973": {"topics": {"Teaching Quality": "negative"}},
  "1974": {"topics": {"Teaching Quality": "positive"}},
  "1975": {"topics": {"Teaching Quality": "positive", "Workload": "negative", "Grading": "negative", "Accessibility": "neutral"}},
  "1976": {"topics": {"Teaching Quality": "positive", "Workload": "positive"}},
  "1977": {"topics": {"Teaching Quality": "negative"}},
  "1978": {"topics": {"Teaching Quality": "positive", "Grading": "neutral", "Accessibility": "positive"}},
  "1979": {"topics": {"Teaching Quality": "neutral", "Grading": "neutral"}},
  "1980": {"topics": {"Teaching Quality": "positive", "Grading": "negative"}},
  "1981": {"topics": {"Teaching Quality": "positive"}},
  "1982": {"topics": {"Teaching Quality": "positive", "Workload": "negative", "Exam Difficulty": "negative"}},
  "1983": {"topics": {"Teaching Quality": "positive"}},
  "1984": {"topics": {"Teaching Quality": "positive"}},
  "1985": {"topics": {"Teaching Quality": "positive", "Grading": "positive"}},
  "1986": {"topics": {"Teaching Quality": "positive"}},
  "1987": {"topics": {"Teaching Quality": "positive", "Workload": "positive", "Exam Difficulty": "positive"}},
  "1988": {"topics": {"Teaching Quality": "positive", "Grading": "positive", "Workload": "positive"}},
  "1989": {"topics": {"Teaching Quality": "positive", "Accessibility": "positive", "Workload": "positive"}},
  "1990": {"topics": {"Teaching Quality": "positive", "Workload": "neutral"}},
  "1991": {"topics": {"Teaching Quality": "positive", "Grading": "neutral", "Accessibility": "positive"}},
  "1992": {"topics": {}},
  "1993": {"topics": {"Teaching Quality": "positive", "Accessibility": "positive"}},
  "1994": {"topics": {}},
  "1995": {"topics": {"Teaching Quality": "negative", "Workload": "negative"}},
  "1996": {"topics": {"Teaching Quality": "positive", "Accessibility": "positive", "Grading": "positive"}},
  "1997": {"topics": {"Teaching Quality": "positive", "Grading": "negative", "Workload": "negative", "Exam Difficulty": "negative"}},
  "1998": {"topics": {"Teaching Quality": "positive", "Accessibility": "positive"}},
  "1999": {"topics": {"Workload": "negative"}},
  "2000": {"topics": {"Teaching Quality": "positive"}},
  "2001": {"topics": {"Teaching Quality": "neutral", "Workload": "positive"}},
  "2002": {"topics": {"Teaching Quality": "negative", "Grading": "neutral"}},
  "2003": {"topics": {"Teaching Quality": "positive"}},
  "2004": {"topics": {"Teaching Quality": "negative"}},
  "2005": {"topics": {"Teaching Quality": "negative", "Grading": "negative"}},
  "2006": {"topics": {"Teaching Quality": "negative"}},
  "2007": {"topics": {"Teaching Quality": "positive", "Grading": "neutral"}},
  "2008": {"topics": {"Grading": "neutral", "Accessibility": "positive"}},
  "2009": {"topics": {"Teaching Quality": "negative", "Workload": "negative"}},
  "2010": {"topics": {"Teaching Quality": "positive", "Grading": "positive", "Workload": "neutral"}},
  "2011": {"topics": {"Teaching Quality": "positive", "Grading": "neutral", "Workload": "positive"}},
  "2012": {"topics": {"Teaching Quality": "neutral", "Workload": "neutral", "Grading": "positive"}},
  "2013": {"topics": {"Teaching Quality": "negative", "Workload": "negative"}},
  "2014": {"topics": {"Teaching Quality": "positive", "Grading": "positive", "Workload": "negative"}},
  "2015": {"topics": {"Teaching Quality": "negative", "Grading": "negative"}},
  "2016": {"topics": {}},
  "2017": {"topics": {"Teaching Quality": "positive", "Accessibility": "positive"}},
  "2018": {"topics": {"Teaching Quality": "positive", "Accessibility": "positive"}},
  "2019": {"topics": {"Teaching Quality": "neutral", "Exam Difficulty": "positive", "Workload": "positive"}},
  "2020": {"topics": {"Teaching Quality": "neutral"}},
  "2021": {"topics": {"Teaching Quality": "positive"}},
  "2022": {"topics": {"Teaching Quality": "positive", "Exam Difficulty": "positive", "Workload": "positive"}},
  "2023": {"topics": {"Teaching Quality": "positive", "Workload": "positive"}},
  "2024": {"topics": {"Teaching Quality": "positive"}},
  "2025": {"topics": {"Grading": "negative"}},
  "2026": {"topics": {"Grading": "negative", "Exam Difficulty": "negative", "Workload": "negative"}},
  "2027": {"topics": {"Teaching Quality": "positive", "Accessibility": "positive"}},
  "2028": {"topics": {"Teaching Quality": "negative"}},
  "2029": {"topics": {"Teaching Quality": "negative", "Grading": "negative"}},
  "2030": {"topics": {"Teaching Quality": "positive"}},
  "2031": {"topics": {"Teaching Quality": "negative"}},
  "2032": {"topics": {"Teaching Quality": "positive", "Workload": "positive"}},
  "2033": {"topics": {"Teaching Quality": "negative"}},
  "2034": {"topics": {"Teaching Quality": "negative"}},
  "2035": {"topics": {"Teaching Quality": "positive", "Accessibility": "positive"}},
  "2036": {"topics": {"Teaching Quality": "positive"}},
  "2037": {"topics": {"Teaching Quality": "positive", "Accessibility": "positive"}},
  "2038": {"topics": {"Teaching Quality": "positive", "Grading": "positive", "Workload": "positive", "Exam Difficulty": "neutral"}},
  "2039": {"topics": {"Workload": "positive", "Grading": "positive"}},
  "2040": {"topics": {"Grading": "negative", "Teaching Quality": "neutral"}},
  "2041": {"topics": {"Teaching Quality": "positive", "Exam Difficulty": "positive"}},
  "2042": {"topics": {"Teaching Quality": "positive"}},
  "2043": {"topics": {"Teaching Quality": "positive", "Accessibility": "positive", "Workload": "positive"}},
  "2044": {"topics": {"Teaching Quality": "neutral", "Workload": "positive"}},
  "2045": {"topics": {"Exam Difficulty": "neutral", "Workload": "positive"}},
  "2046": {"topics": {"Teaching Quality": "negative", "Exam Difficulty": "neutral", "Grading": "positive"}},
  "2047": {"topics": {"Teaching Quality": "positive"}},
  "2048": {"topics": {"Teaching Quality": "positive", "Workload": "positive", "Exam Difficulty": "neutral"}},
  "2049": {"topics": {"Workload": "negative", "Teaching Quality": "positive"}},
  "2050": {"topics": {"Grading": "negative", "Teaching Quality": "negative"}},
  "2051": {"topics": {"Teaching Quality": "positive", "Grading": "positive", "Exam Difficulty": "neutral"}},
  "2052": {"topics": {"Teaching Quality": "negative", "Grading": "negative"}},
  "2053": {"topics": {"Teaching Quality": "positive", "Workload": "positive", "Exam Difficulty": "positive"}},
  "2054": {"topics": {"Teaching Quality": "positive", "Exam Difficulty": "negative", "Grading": "positive"}},
  "2055": {"topics": {"Teaching Quality": "positive", "Accessibility": "positive"}},
  "2056": {"topics": {"Teaching Quality": "positive", "Accessibility": "positive", "Grading": "positive"}},
  "2057": {"topics": {"Teaching Quality": "positive", "Exam Difficulty": "positive"}},
  "2058": {"topics": {"Teaching Quality": "positive"}},
  "2059": {"topics": {"Teaching Quality": "positive", "Grading": "positive"}},
  "2060": {"topics": {"Exam Difficulty": "negative", "Workload": "neutral"}},
  "2061": {"topics": {"Teaching Quality": "positive"}},
  "2062": {"topics": {"Teaching Quality": "positive", "Exam Difficulty": "positive", "Workload": "positive"}},
  "2063": {"topics": {"Teaching Quality": "positive", "Grading": "positive", "Workload": "positive"}},
  "2064": {"topics": {"Teaching Quality": "positive", "Exam Difficulty": "positive", "Accessibility": "positive"}},
  "2065": {"topics": {"Teaching Quality": "positive", "Grading": "positive"}},
  "2066": {"topics": {"Teaching Quality": "positive"}},
  "2067": {"topics": {"Teaching Quality": "positive", "Workload": "positive"}},
  "2068": {"topics": {"Teaching Quality": "positive", "Grading": "positive", "Workload": "positive"}},
  "2069": {"topics": {"Teaching Quality": "neutral", "Workload": "neutral"}},
  "2070": {"topics": {"Teaching Quality": "positive", "Exam Difficulty": "positive"}},
  "2071": {"topics": {"Teaching Quality": "negative"}},
  "2072": {"topics": {"Teaching Quality": "positive", "Accessibility": "positive"}},
  "2073": {"topics": {"Teaching Quality": "negative", "Grading": "negative", "Accessibility": "negative"}},
  "2074": {"topics": {"Teaching Quality": "positive", "Exam Difficulty": "positive"}},
  "2075": {"topics": {"Teaching Quality": "positive", "Exam Difficulty": "neutral", "Workload": "neutral"}},
  "2076": {"topics": {"Teaching Quality": "positive", "Exam Difficulty": "positive", "Workload": "positive"}},
  "2077": {"topics": {"Teaching Quality": "positive", "Exam Difficulty": "positive", "Workload": "positive"}},
  "2078": {"topics": {"Teaching Quality": "positive", "Accessibility": "positive"}}
}
